meshing/__init__.py
meshing/_utils.py
meshing-2.0.7.dist-info/METADATA
meshing-2.0.7.dist-info/WHEEL
meshing-2.0.7.dist-info/top_level.txt
meshing-2.0.7.dist-info/RECORD
