Metadata-Version: 2.1
Name: meshing
Version: 2.0.7
Summary: Simple Python client library for https://devnull.cn/meshing
Home-page: https://devnull.cn
Author: Xizhen Du
Author-email: xizhendu@gmail.com
Requires-Dist: requests
Requires-Dist: theid
